laylib/__init__.py
laylib/default_engine.py
laylib/environment.py
laylib/resources.py
laylib/util.py
laylib-1.1.9.dist-info/LICENCE.txt
laylib-1.1.9.dist-info/METADATA
laylib-1.1.9.dist-info/WHEEL
laylib-1.1.9.dist-info/top_level.txt
laylib-1.1.9.dist-info/RECORD
