Metadata-Version: 2.1
Name: laylib
Version: 1.1.9
Summary: A 2-D engine for Python and pygame
Home-page: https://github.com/Layto888/laylib
Author: Amardjia Amine
Author-email: amardjia.amine@gmail.com
License: MIT License
Platform: UNKNOWN
Classifier: Programming Language :: Python :: 3
Classifier: License :: OSI Approved :: MIT License
Classifier: Operating System :: OS Independent
